{
  "searchParameters": {
    "q": "rare coin appraisal near me",
    "gl": "us",
    "hl": "en",
    "type": "search",
    "engine": "google"
  },
  "organic": [
    {
      "title": "Coin Dealers near Lancaster, PA | Better Business Bureau",
      "link": "https://www.bbb.org/us/pa/lancaster/category/coin-dealers",
      "snippet": "Dennis Eckenrode Rare Coins, Inc. Coin Dealers. BBB Rating: A+. not BBB accredited. (717) 272-4579. 20 E Penn Ave, Cleona, PA 17042-3221. Copenhaver Coin ...",
      "attributes": {
        "Missing": "appraisal | Show results with:appraisal"
      },
      "position": 1
    },
    {
      "title": "BEST of Lancaster, PA Coin Shop - Yelp",
      "link": "https://www.yelp.com/search?find_desc=Coin+Shop&find_loc=Lancaster%2C+PA",
      "snippet": "Top 10 Best Coin Shop Near Lancaster, Pennsylvania ; 1. Security Rare Coins. 4.2 (13 reviews) ; 2. Susquehanna Coin Company. 2.8 (4 reviews) ; 3. Steinmetz Coins & ...",
      "position": 2
    },
    {
      "title": "We Buy Gold, Coins & Jewelry | Security Rare Coins, Lancaster PA",
      "link": "https://www.securitycoinsandgold.com/",
      "snippet": "Lancaster, PA's most trusted place to buy or sell gold and rare coins for over 35 years! Highest Prices Paid. Fair and honest dealings. Get Your Cash Today.",
      "sitelinks": [
        {
          "title": "Contact Us",
          "link": "https://www.securitycoinsandgold.com/contact-us/"
        },
        {
          "title": "Services",
          "link": "https://www.securitycoinsandgold.com/services/"
        },
        {
          "title": "Silver & Metals",
          "link": "https://www.securitycoinsandgold.com/services/silver-metals/"
        },
        {
          "title": "Coins & Paper Money",
          "link": "https://www.securitycoinsandgold.com/services/coins-paper-money/"
        }
      ],
      "position": 3
    },
    {
      "title": "Steinmetz Coins & Currency – We buy and sell coins, currency and ...",
      "link": "https://steinmetzcoins.com/",
      "snippet": "YORK LOCATION: 1001 Haines Road York, PA 17402. Phone: (717) 757-6980. Hours: Monday 9:30-4:30. Tuesday 9:30-4:30. Wednesday 9:30-12:00. Thursday 9:30-4:30",
      "position": 4
    },
    {
      "title": "Security Rare Coins - 1513 Lititz Pike, Lancaster, Pennsylvania - Yelp",
      "link": "https://www.yelp.com/biz/security-rare-coins-lancaster",
      "snippet": "Very friendly and fair Always enjoy doing business with them. Easy to find Experts on silver and gold and any old coin you may find. Business owner information.",
      "rating": 4.2,
      "ratingCount": 13,
      "position": 5
    },
    {
      "title": "Pennsylvania Rare Coin Dealer - American Rarities",
      "link": "https://americanrarities.com/pennsylvania-rare-coin-dealer/",
      "snippet": "We are a Pennsylvania Coin Dealer buying Rare Coins, Gold and Silver Bullion, and U.S. Paper Currency. Free appraisals and offer.",
      "position": 6
    },
    {
      "title": "Sell Coins in Pennsylvania - Rare Coin Dealer | Free Appraisals",
      "link": "https://coinfully.com/location-page/pennsylvania-coin-buyer/",
      "snippet": "Sell your coins in Pennsylvania with Coinfully. Get free appraisals and the best prices for your rare coins. Trusted Pennsylvania coin buyer.",
      "position": 7
    },
    {
      "title": "Coin Dealers Near Me | Better Business Bureau",
      "link": "https://www.bbb.org/near-me/coin-dealers",
      "snippet": "You want to find a coin collector or coin appraiser who is ethical and won't rip you off. BBB can help you find highly rated and BBB Accredited coin shops near ...",
      "position": 8
    },
    {
      "title": "Find Coin Shops & Dealers | Coin Dealer Locator - NGC",
      "link": "https://www.ngccoin.com/coin-dealer-locator/",
      "snippet": "Use the NGC Dealer Locator to find local coin shops and dealers in your area. Search dealers by store name or location, including city, state, country or ...",
      "sitelinks": [
        {
          "title": "Coin Appraisals",
          "link": "https://www.ngccoin.com/coin-dealer-locator/results/?services=5-coin-appraisals"
        },
        {
          "title": "Coin Supplies",
          "link": "https://www.ngccoin.com/coin-dealer-locator/results/?services=132-coin-supplies"
        },
        {
          "title": "US Coins",
          "link": "https://www.ngccoin.com/coin-dealer-locator/results/?specialties=19-us-coins"
        },
        {
          "title": "Morgan and Peace Dollars",
          "link": "https://www.ngccoin.com/coin-dealer-locator/results/?specialties=13-morgan-and-peace-dollars"
        }
      ],
      "position": 9
    },
    {
      "title": "Find Coin Dealers Near You - Lancaster",
      "link": "https://coin-dealer-directory.money.org/lancaster",
      "snippet": "Cabbage Coins is a Buyer and Seller of Rare Coins, Gold, and Silver Bars located right in the heart of beautiful Lancaster County Pennsylvania.",
      "position": 10
    }
  ],
  "places": [
    {
      "title": "New Holland Coins and Vintage",
      "address": "New Holland, PA",
      "rating": 4.6,
      "ratingCount": 49,
      "cid": "15368388542061303398"
    },
    {
      "title": "Security Rare Coins",
      "address": "Lancaster, PA",
      "rating": 4.4,
      "ratingCount": 82,
      "cid": "11716011595944976129"
    },
    {
      "title": "East Coast Coin & Stamp",
      "address": "Shillington, PA",
      "rating": 3.1,
      "ratingCount": 12,
      "cid": "6326195712743586884"
    }
  ],
  "peopleAlsoAsk": [
    {
      "question": "How do you get coins appraised without getting ripped off?",
      "snippet": "You can pay a professional appraiser to do it (only worth it if you already know the collection is worth a significant pile of money). You can ask your local coin shop for help. Most likely they will give you a very low-ball estimate. Or you can do it the hard (and fun) way. Study your coin collection.",
      "title": "How to get an honest appraisal of a coin collection of all US coins - Quora",
      "link": "https://www.quora.com/How-can-I-get-an-honest-appraisal-of-a-coin-collection-of-all-US-coins"
    },
    {
      "question": "How do I know if a coin I have is valuable?",
      "snippet": "A coin is ultimately worth what the collector is willing to pay for it, but there are factors you should consider before committing to a price. This can include the condition of the coin, its design, mintage figure and what it's made of.",
      "title": "Guide to Getting a Fair Price for a Coin | The Royal Mint",
      "link": "https://www.royalmint.com/stories/collect/guide-to-getting-a-fair-price-for-a-coin/"
    },
    {
      "question": "How do you know if a coin appraiser is legit?",
      "snippet": "Research Appraisers: Look for reputable coin appraisers or numismatists. You can find them through: - Professional organizations like the American Numismatic Association (ANA). - Local coin shops or dealers with good reviews. - Online directories of certified appraisers.",
      "title": "How to have a coin collection appraised - Quora",
      "link": "https://www.quora.com/How-do-I-have-a-coin-collection-appraised"
    }
  ],
  "relatedSearches": [
    {
      "query": "Golden Eagle Coins"
    },
    {
      "query": "rare coin appraisal near ephrata, pa"
    },
    {
      "query": "Rare coin appraisal near me open now"
    },
    {
      "query": "Rare coin appraisal near me for cash"
    },
    {
      "query": "Rare coin appraisal near me free"
    },
    {
      "query": "Rare coin appraisal near me prices"
    },
    {
      "query": "Best rare coin appraisal near me"
    },
    {
      "query": "Coin Dealers Lancaster PA"
    },
    {
      "query": "Sell coins for cash near me"
    }
  ],
  "credits": 1
}