{
  "searchParameters": {
    "q": "old pocket knives identification",
    "gl": "us",
    "hl": "en",
    "type": "search",
    "engine": "google"
  },
  "organic": [
    {
      "title": "Vintage Pocket Knife Identification",
      "link": "https://allaboutpocketknives.com/knife_forum/viewtopic.php?t=80608",
      "snippet": "I'm looking for some help identifying this pocket knife. It looks like the Knife Brand is wore off. The only stamp is either RC600 or R0600.",
      "date": "Nov 5, 2023",
      "sitelinks": [
        {
          "title": "Old folding knife identification help - All About Pocket Knives",
          "link": "https://allaboutpocketknives.com/knife_forum/viewtopic.php?t=76535"
        },
        {
          "title": "Help Identifying Vintage Unmarked Knife - All About Pocket Knives",
          "link": "https://allaboutpocketknives.com/knife_forum/viewtopic.php?t=82559"
        }
      ],
      "position": 1
    },
    {
      "title": "How to identify the maker or brand of an old knife - The Cutting Edge",
      "link": "https://blog.knife-depot.com/how-to-identify-an-old-knife/",
      "snippet": "The first, and most obvious, place to start is with the knife itself. Look for any sort of symbols, initials, or identifying marks.",
      "date": "Mar 1, 2024",
      "position": 2
    },
    {
      "title": "Old Pocket Knives",
      "link": "https://oldpocketknives.com/",
      "snippet": "Some collectors seek out specific knife patterns such as barlows, whittlers, trappers or the popular elephant toe. Other collectors look for a specific handle ...",
      "sitelinks": [
        {
          "title": "Remington Knives",
          "link": "https://oldpocketknives.com/remington-knives/"
        },
        {
          "title": "Northwoods Knives",
          "link": "https://oldpocketknives.com/northwoods-knives/"
        },
        {
          "title": "Ruana Knives",
          "link": "https://oldpocketknives.com/vintage-ruana-knives-bonner-mt/"
        },
        {
          "title": "Vintage Case Knives",
          "link": "https://oldpocketknives.com/vintage-case-knives/"
        }
      ],
      "position": 3
    },
    {
      "title": "Amazon.com: Big Book of Pocket Knives : Identification & Values",
      "link": "https://www.amazon.com/Big-Book-Pocket-Knives-Identification/dp/1574321781",
      "snippet": "Big Book of Pocket Knives enables collectors to examine knife and cutlery products from more than 20 cutlery companies. Hundreds of illustrations are ...",
      "position": 4
    },
    {
      "title": "Here Is How I Find More Information About Antique Pocket Knives ...",
      "link": "https://www.youtube.com/watch?v=RlrLj3fe-bw",
      "snippet": "... identifying makers/markings. 17:01 · Go to channel · Finding a Treasure in a lot of old POCKET KNIVES from eBay - Unboxing Knife.",
      "date": "Nov 15, 2022",
      "position": 5
    },
    {
      "title": "Case Pocket Knife Age Identification - All About Pocket Knives",
      "link": "https://www.allaboutpocketknives.com/catalog/content/case-knife-age-identification",
      "snippet": "In 2000, Case developed a dating system using an old style Case XX stamp along with a mix of dots and x's both above the Case XX symbol and below. Case ...",
      "position": 6
    },
    {
      "title": "Identify old pocket knife? : r/knifeclub - Reddit",
      "link": "https://www.reddit.com/r/knifeclub/comments/15k7kxb/identify_old_pocket_knife/",
      "snippet": "I found this interesting old pocketknife in my grandfather's toolbox. Can anyone identify it?",
      "date": "Aug 7, 2023",
      "sitelinks": [
        {
          "title": "Help Identifying Grandfather's Pocket Knife? : r/knifeclub",
          "link": "https://www.reddit.com/r/knifeclub/comments/14j55qs/help_identifying_grandfathers_pocket_knife/"
        },
        {
          "title": "Old pocket knife identification",
          "link": "https://www.reddit.com/r/knife/comments/13odgsm/old_pocket_knife_identification/"
        }
      ],
      "position": 7
    },
    {
      "title": "Case Pocket Knives | How To Identify and Date These ... - YouTube",
      "link": "https://www.youtube.com/watch?v=ttr-iygD3y0",
      "snippet": "We show you the different Case knives that you might find at yard sales or when you're out picking and how to recognize them.",
      "date": "Mar 19, 2023",
      "position": 8
    },
    {
      "title": "Rare vintage knives - Old Pocket Knives",
      "link": "https://oldpocketknives.com/rare-vintage-knives/",
      "snippet": "These rare vintage knives include Case, Remington, Winchester and more. In addition, I have included some 19th century bowie knives and the top fixed blade ...",
      "position": 9
    }
  ],
  "images": [
    {
      "title": "How to Clean & Restore a Vintage Pocketknife | The Art of Manliness",
      "imageUrl": "https://content.artofmanliness.com/uploads/2016/01/knives3.jpg",
      "link": "https://www.artofmanliness.com/skills/how-to/how-to-restore-a-vintage-antique-pocket-knife/"
    },
    {
      "title": "Broken, Battered, Beat-Up, Bruised But Beautiful Old Knives - All ...",
      "imageUrl": "https://www.allaboutpocketknives.com/images/forum_archives/ab101-MillerBros-439e97ca.jpg",
      "link": "https://www.allaboutpocketknives.com/knife_forum/viewtopic.php?t=25402"
    },
    {
      "title": "Old Pocket Knives – A resource for collectors of old pocket knives",
      "imageUrl": "https://oldpocketknives.com/wp-content/uploads/2023/06/62537F08-317F-45C3-B254-C672AE8CCAA1-e1704639333805.jpeg",
      "link": "https://oldpocketknives.com/"
    },
    {
      "title": "Identify old pocket knife? : r/knifeclub",
      "imageUrl": "https://i.redd.it/identify-old-pocket-knife-v0-nav1ht0fklgb1.jpg?width=4032&format=pjpg&auto=webp&s=488db2ce2243449f8ecb2c503b7b55fd811acda6",
      "link": "https://www.reddit.com/r/knifeclub/comments/15k7kxb/identify_old_pocket_knife/"
    },
    {
      "title": "Big Book of Pocket Knives : Identification & Values (Big Book of ...",
      "imageUrl": "https://pictures.abebooks.com/isbn/9781574323962-us.jpg",
      "link": "https://www.abebooks.com/9781574323962/Big-Book-Pocket-Knives-Identification-1574323962/plp"
    },
    {
      "title": "Amazon.com: Big Book of Pocket Knives : Identification & Values ...",
      "imageUrl": "https://m.media-amazon.com/images/I/81QhPJsfO0L._AC_UF1000,1000_QL80_.jpg",
      "link": "https://www.amazon.com/Big-Book-Pocket-Knives-Identification/dp/1574321781"
    },
    {
      "title": "Identify vintage pocket knife | Collectors Weekly",
      "imageUrl": "https://d3h6k4kfl8m9p0.cloudfront.net/stories/644tBGtqetmjyrp0iB-cPQ.jpg",
      "link": "https://www.collectorsweekly.com/stories/187160-identify-vintage-pocket-knife"
    },
    {
      "title": "Age That Old Knife By Deciphering Its Blade Stamp - Game & Fish",
      "imageUrl": "https://content.osgnetworks.tv/photopacks/age-that-knife_469970/469971_gaf-knivesbarlow-1200x800_hero_1200x800.jpg",
      "link": "https://www.gameandfishmag.com/editorial/age-old-knife-by-blade-stamp/469972"
    },
    {
      "title": "Help identifying old folding blade I found. : r/SWORDS",
      "imageUrl": "https://i.redd.it/help-identifying-old-folding-blade-i-found-v0-kd72vcaj8p191.jpg?width=3024&format=pjpg&auto=webp&s=507700cf2b1d065f9cf2b9b35e3ca5eb3f66865f",
      "link": "https://www.reddit.com/r/SWORDS/comments/uxszzm/help_identifying_old_folding_blade_i_found/"
    }
  ],
  "peopleAlsoAsk": [
    {
      "question": "What are the vintage pocket knives brands?",
      "snippet": "Some collectors look for certain makers such as Case, Remington, or KA-BAR while others focus on a region of manufacture such as early New England brands like Waterville, Holley or Empire. Some collectors seek out specific knife patterns such as barlows, whittlers, trappers or the popular elephant toe.",
      "title": "Old Pocket Knives",
      "link": "https://oldpocketknives.com/"
    },
    {
      "question": "What makes pocket knives collectible?",
      "snippet": "These collectible knives are typically some form of exclusive knives, limited edition knives, limited run knives, scrimshawed knives, and knife series. Most collectible knives are made with very fine, exacting detail and rare materials.",
      "title": "Collectible, Limited, or Exclusive Knives | AGRussell.com",
      "link": "https://agrussell.com/collectible-knives"
    },
    {
      "question": "How do you know how old a case knife is?",
      "snippet": "The Case blade tang dating system allows you to identify your knife with a year or era in which the knife was manufactured. The dating symbols are found on the tang stamps at the base of the knife's main blade. In 1970, Case added ten dots beneath the “U.S.A” on all knife tangs. Each year a dot was removed.",
      "title": "FAQs | Case Knives – caseknives.com",
      "link": "https://caseknives.com/pages/frequently-asked-questions"
    }
  ],
  "relatedSearches": [
    {
      "query": "Vintage old pocket knives identification"
    },
    {
      "query": "Old pocket knives identification by year"
    },
    {
      "query": "Pocket knife identification website"
    },
    {
      "query": "Old pocket knives identification app"
    },
    {
      "query": "Knife identification app"
    },
    {
      "query": "Knife identification website free"
    },
    {
      "query": "Knife identification Chart"
    },
    {
      "query": "Case knife Identification and value guide"
    }
  ],
  "credits": 1
}