{
  "searchParameters": {
    "q": "antique toys value",
    "gl": "us",
    "hl": "en",
    "type": "search",
    "engine": "google"
  },
  "organic": [
    {
      "title": "Vintage & Antique Toys for sale - eBay",
      "link": "https://www.ebay.com/b/Vintage-Antique-Toys/717/bn_1860860",
      "snippet": "On eBay, you will find a wide range of antique miniature trucks, convertible cars, battleships, and various other toys worth a look. If buying for kids, you can ...",
      "position": 1
    },
    {
      "title": "Toy Appraisals and Old Toy Collection Help - Antique Toys",
      "link": "https://www.antiquetoys.com/toy-appraisals/",
      "snippet": "Antique Toys can appraise your toy based on experience; backed by hundreds of catalogs, hundreds of auction books, thousands of results records, and our ...",
      "sitelinks": [
        {
          "title": "Toy Appraisal Start",
          "link": "https://www.antiquetoys.com/toy-appraisals/#:~:text=Toy%20Appraisal%20Start"
        },
        {
          "title": "Pre Appraisal",
          "link": "https://www.antiquetoys.com/toy-appraisals/#:~:text=Pre%20Appraisal"
        },
        {
          "title": "So Contact Us!",
          "link": "https://www.antiquetoys.com/toy-appraisals/#:~:text=So%20Contact%20Us%21"
        }
      ],
      "position": 2
    },
    {
      "title": "The Most Expensive Vintage Toys of All Time - Public.com",
      "link": "https://public.com/learn/most-expensive-valuable-vintage-toys",
      "snippet": "1) Barbie by Stefano Canturi, 2010 $302,500 at Christie's on October 20, 2010 · 2) G.I. Joe, 1963 · 3) Star Wars Rocket Firing Boba Fett, 1979 $185,850 at Hake's ...",
      "position": 3
    },
    {
      "title": "How to Find, Store, and Value the Collectible Toys From Your ...",
      "link": "https://www.americasantiquemall.com/post/how-to-find-store-and-value-the-collectible-toys-from-your-childhood",
      "snippet": "When it comes to the value of antique toys, the condition is always a factor. But there are many different condition options to consider ...",
      "date": "Oct 9, 2023",
      "position": 4
    },
    {
      "title": "What Are The Most Valuable Antique Toys - PGS Gold & Coin",
      "link": "https://pgsgoldandcoin.com/2024/06/28/what-are-the-most-valuable-antique-toys/",
      "snippet": "The value of antique toys can vary greatly depending on factors such as rarity, condition, age, and historical significance.",
      "date": "Jun 28, 2024",
      "position": 5
    },
    {
      "title": "Check your garage for these top 15 most valuable old toys",
      "link": "https://www.usatoday.com/story/money/2023/12/19/old-toys-worth-money/71976097007/",
      "snippet": "Kenner Star Wars action figures, Darth Vader and Obi-Wan Kenobi were sold for a combined total of more than $100,000. The action figures were ...",
      "date": "Dec 19, 2023",
      "position": 6
    },
    {
      "title": "19 Vintage Toys That Are Valuable Treasures in Disguise",
      "link": "https://wealthgang.com/16-vintage-toys-worth-more-than-your-rent/",
      "snippet": "19 Vintage Toys That Are Valuable Treasures in Disguise · 1. G.I. Joe Action Figures · 2. Beanie Babies · 3. Teddy Ruxpin · 4. Trolls · 5. PEZ ...",
      "date": "Feb 9, 2025",
      "sitelinks": [
        {
          "title": "1. G.I. Joe Action Figures",
          "link": "https://wealthgang.com/16-vintage-toys-worth-more-than-your-rent/#:~:text=1.%20G.I.%20Joe%20Action%20Figures"
        },
        {
          "title": "5. Pez Dispensers",
          "link": "https://wealthgang.com/16-vintage-toys-worth-more-than-your-rent/#:~:text=5.%20PEZ%20Dispensers"
        },
        {
          "title": "12. Cabbage Patch Dolls",
          "link": "https://wealthgang.com/16-vintage-toys-worth-more-than-your-rent/#:~:text=12.%20Cabbage%20Patch%20Dolls"
        }
      ],
      "position": 7
    },
    {
      "title": "How Much Are These VINTAGE Toys Worth? - YouTube",
      "link": "https://www.youtube.com/watch?v=l4FSJ0lC-oo",
      "snippet": "TOPIC: How much are these vintage collectible toys selling for on ebay. Like my comic book videos, we take a deeper dive into the recent ...",
      "date": "Apr 29, 2024",
      "position": 8
    },
    {
      "title": "The Most Expensive Vintage Toys of All Time",
      "link": "https://www.playgroundequipment.com/the-most-expensive-vintage-toys-of-all-time/",
      "snippet": "The Most Expensive Vintage Toys of All Time ; 1. Barbie by Stefano Canturi. Sold for $302,500 in 2010 ; 2. 1963 G.I. Joe. Sold for $200,000 in 2003 ; 3. 1979 Star ...",
      "sitelinks": [
        {
          "title": "1. Barbie By Stefano Canturi",
          "link": "https://www.playgroundequipment.com/the-most-expensive-vintage-toys-of-all-time/#:~:text=1.%20Barbie%20by%20Stefano%20Canturi"
        },
        {
          "title": "Sold For $302,500 In 2010",
          "link": "https://www.playgroundequipment.com/the-most-expensive-vintage-toys-of-all-time/#:~:text=Sold%20for%20%24302%2C500%20in%202010"
        },
        {
          "title": "Sold For $110,000 In 2000",
          "link": "https://www.playgroundequipment.com/the-most-expensive-vintage-toys-of-all-time/#:~:text=Sold%20for%20%24110%2C000%20in%202000"
        }
      ],
      "position": 9
    },
    {
      "title": "How Much Are My Vintage Action Figures and Toys Worth?",
      "link": "https://entertainment.ha.com/worth/action-figures.s",
      "snippet": "Several online resources can help you determine the value of your toys. One such resource is the archive of Heritage Auctions' past sales.",
      "position": 10
    }
  ],
  "peopleAlsoAsk": [
    {
      "question": "How do I know if my toys are worth money?",
      "snippet": "Firstly, rarity is key. The more limited or rare the item, the more valuable it's likely to be. Toys that were part of limited production runs or exclusive collections often fetch higher prices, as do items in excellent condition, particularly if they're still in their original packaging.",
      "title": "Could Your Vintage Toys Be Worth Thousands? - Homeprotect",
      "link": "https://www.homeprotect.co.uk/blog/hidden-treasures-toys"
    },
    {
      "question": "Which old toys are worth the most money?",
      "snippet": "HERE'S A LOOK AT SOME OF THE MOST EXPENSIVE VINTAGE TOYS THAT COLLECTORS ARE SNATCHING UP.\n1\nG.I. Joe Action Figures. ...\n2\nBeanie Babies. rhydonsharpedo/eBay. ...\n3\nTeddy Ruxpin. ronlocklear2012 / ebay. ...\n4\nTrolls. klmar51 / ebay. ...\n5\nPEZ Dispensers. dobbybouglas/ebay. ...\n6\nRedline Hot Wheels. m62c63t91t93/eBay. ...\n7\nFurbies. ...\n8\n'Star Wars' Action Figures.",
      "title": "19 Vintage Toys That Are Valuable Treasures in Disguise",
      "link": "https://wealthgang.com/16-vintage-toys-worth-more-than-your-rent/"
    },
    {
      "question": "What toys are considered vintage?",
      "snippet": "Vintage toys are generally considered to be items that were produced 20 to 100 years ago. Unlike modern toys, these often reflect the design, materials, and cultural influences of the time in which they were created.",
      "title": "How to Identify and Date Vintage Toys - ReKennect",
      "link": "https://rekennect.com/blogs/vintage-toys/identify-date/"
    }
  ],
  "relatedSearches": [
    {
      "query": "Most valuable antique toys value guide"
    },
    {
      "query": "Rare antique toys value"
    },
    {
      "query": "Most valuable antique toys value"
    },
    {
      "query": "Rare old toys worth millions"
    },
    {
      "query": "Vintage toys 1960s"
    },
    {
      "query": "Vintage 80s toys worth money"
    },
    {
      "query": "Rare old toys worth millions from the 90s"
    },
    {
      "query": "Ebay Vintage Toys 1960"
    }
  ],
  "credits": 1
}