{
  "searchParameters": {
    "q": "luncheon of the boating party value",
    "gl": "us",
    "hl": "en",
    "type": "search",
    "engine": "google"
  },
  "organic": [
    {
      "title": "The Luncheon of the Boating Party 1881 | Oil Painting Reproduction",
      "link": "https://www.reproduction-gallery.com/oil-painting/1009965985/the-luncheon-of-the-boating-party-1881-by-pierre-auguste-renoir/?srsltid=AfmBOoqXrlS67mqNGK5jPQm347ZzXcmJADFYHxp0vKLn_VvbTb0AxnGr",
      "snippet": "Choose Painting Size (Height x Width) · 22.0 x 29.5\" (56 x 75 cm) = $299 · 23.6 x 31.5\" (60 x 80 cm) = $323 · 24.8 x 33.5\" (63 x 85 cm) = $349 · 26.4 x 35.4\" (67 x ...",
      "position": 1
    },
    {
      "title": "Luncheon of the Boating Party | Renoir | Painting Reproduction 1901",
      "link": "https://www.topofart.com/artists/Renoir/art-reproduction/1901/Luncheon-of-the-Boating-Party.php?srsltid=AfmBOoogfgYx1iiG4XFQVVl-o9FiR3c-CQ0rQ4gHPFTNL_tzA1K8TKCB",
      "snippet": "Luncheon of the Boating Party, c.1880/81 by Pierre-Auguste Renoir | Museum Quality Oil Painting Reproduction and Canvas Print 1901 | TOPofART.",
      "rating": 5,
      "ratingCount": 2,
      "position": 2
    },
    {
      "title": "Luncheon of the Boating Party: Renoir's Most Happening Art",
      "link": "https://www.portraitflip.com/blog/luncheon-of-the-boating-party/?srsltid=AfmBOorLQEk1e4_1CcWNcy1M6A7htuIP0ptV85q44Cm9f62Rjfv6WStI",
      "snippet": "Renoir's Luncheon of the Boating Party is worth over 12 million dollars and it can even be more as the Luncheon party art isn't for sale. This ...",
      "date": "May 4, 2023",
      "sitelinks": [
        {
          "title": "History & Significance",
          "link": "https://www.portraitflip.com/blog/luncheon-of-the-boating-party/#h-history-amp-significance"
        },
        {
          "title": "Composition and Analysis",
          "link": "https://www.portraitflip.com/blog/luncheon-of-the-boating-party/#h-composition-and-analysis-nbsp"
        }
      ],
      "position": 3
    },
    {
      "title": "Brush Strokes Fine Art Inc Luncheon of The Boating Party Pierre",
      "link": "https://www.ebay.com/itm/166762163450",
      "snippet": "Painting is in mint condition. Contains a bit of dust in the corners. The portrait is 8\" H X 10\" W.",
      "position": 4
    },
    {
      "title": "Expert Appraisals: Value of Pierre-Auguste Renoir Paintings",
      "link": "https://www.justanswer.com/appraisals/jgs4p-look-value-pierre-augusta-renoir-painting.html",
      "snippet": "... value will be decorative, so around $60- $100 for this one ... Nota please tell me about this piece luncheon of the boating party by Pierre auguste Renoir.",
      "position": 5
    },
    {
      "title": "The Luncheon Of The Boating Party Magnet Pierre Auguste Renoir ...",
      "link": "https://www.ebay.com/itm/125694799427",
      "snippet": "The Luncheon Of The Boating Party Magnet Pierre Auguste Renoir 1997. Excellent condition. ... For the price, these are an exceptional value. I recommend this ...",
      "currency": "$",
      "price": 3.62,
      "position": 6
    },
    {
      "title": "Pierre-Auguste Renoir | Luncheon of the Boating Party (1880-1881)",
      "link": "https://www.artsy.net/artwork/pierre-auguste-renoir-luncheon-of-the-boating-party",
      "snippet": "From Phillips Collection, Pierre-Auguste Renoir, Luncheon of the Boating Party (1880-1881), Oil on canvas, 51 1/4 × 69 13/100 in.",
      "position": 7
    },
    {
      "title": "About the value of art - The Oklahoman",
      "link": "https://www.oklahoman.com/story/news/1982/10/17/about-the-value-of-art/62869939007/",
      "snippet": "Pierre Renoir's \"Luncheon of the Boating Party\" 12 million to 15 million dollars, and maybe even more \"A top piece of work.\" So, if these ...",
      "date": "Oct 17, 1982",
      "position": 8
    },
    {
      "title": "Luncheon of the Boating Party - Wikipedia",
      "link": "https://en.wikipedia.org/wiki/Luncheon_of_the_Boating_Party",
      "snippet": "It was purchased from the artist by the dealer-patron Paul Durand-Ruel and bought in 1923 (for $125,000) from his son by industrialist Duncan Phillips, who ...",
      "sitelinks": [
        {
          "title": "Aline Charigot",
          "link": "https://en.wikipedia.org/wiki/Aline_Charigot"
        },
        {
          "title": "The Phillips Collection",
          "link": "https://en.wikipedia.org/wiki/The_Phillips_Collection"
        },
        {
          "title": "Still life",
          "link": "https://en.wikipedia.org/wiki/Still_life"
        },
        {
          "title": "Ellen Andrée",
          "link": "https://en.wikipedia.org/wiki/Ellen_Andr%C3%A9e"
        }
      ],
      "position": 9
    },
    {
      "title": "Luncheon Of The Boating Party - 1st Art Gallery",
      "link": "https://www.1st-art-gallery.com/Pierre-Auguste-Renoir/Luncheon-Of-The-Boating-Party.html?srsltid=AfmBOorj2hcNPAG_ptCfaEPTyaiWGtxjuEWcJWTGlstgNKARvymoOnak",
      "snippet": "Buy the Luncheon Of The Boating Party Reproduction by Pierre Auguste Renoir. Choose a custom size for your favorite oil painting. Order in a few clicks!",
      "attributes": {
        "Missing": "value | Show results with:value"
      },
      "rating": 5,
      "ratingCount": 2065,
      "position": 10
    }
  ],
  "peopleAlsoAsk": [
    {
      "question": "Where is Luncheon of the Boating Party now?",
      "snippet": "The Phillips Collection\nIt is now in The Phillips Collection in Washington, D.C. It shows a richness of form, a fluidity of brush stroke, and a flickering light.",
      "title": "Luncheon of the Boating Party - Wikipedia",
      "link": "https://en.wikipedia.org/wiki/Luncheon_of_the_Boating_Party"
    },
    {
      "question": "How much did Renoir sell his paintings for?",
      "snippet": "Renoir painted about 4000 paintings that have sold at auction for as much as $78.1 million (in 1990). The largest collection of Renoir paintings is at the Barnes Foundation in Philadelphia, Pennsylvania, United States.",
      "title": "List of paintings by Pierre-Auguste Renoir - Wikipedia",
      "link": "https://en.wikipedia.org/wiki/List_of_paintings_by_Pierre-Auguste_Renoir"
    },
    {
      "question": "What is the most valuable Renoir?",
      "snippet": "Bal du moulin de la Galette (1876), by French artist Pierre-Auguste Renoir, sold for $78.1 million (£46.17 million) at Sotheby's New York, USA, on 17 May 1990.",
      "title": "Most expensive painting by Renoir sold at auction",
      "link": "https://www.guinnessworldrecords.com/world-records/769008-most-expensive-painting-by-renoir-sold-at-auction"
    }
  ],
  "relatedSearches": [
    {
      "query": "Luncheon of the boating party value pdf"
    },
    {
      "query": "Pierre auguste renoir luncheon of the boating party value"
    },
    {
      "query": "Luncheon of the Boating Party Print"
    },
    {
      "query": "Luncheon of the Boating Party analysis"
    },
    {
      "query": "Luncheon of the Boating Party location"
    },
    {
      "query": "Caillebotte Boating Party"
    },
    {
      "query": "Renoir garden Party"
    }
  ],
  "credits": 1
}