{
  "searchParameters": {
    "q": "how much is a 1955 d penny worth",
    "gl": "us",
    "hl": "en",
    "type": "search",
    "engine": "google"
  },
  "answerBox": {
    "snippet": "\n1955 Wheat Penny Value Chart*\n\n\nMint mark\nMS63\nMS67\n1955 (P) No Mint Mark Wheat Penny Value\n$9\n$850\n1955 D Wheat Penny Value\n$8\n$575\n1955 S Wheat Penny Value\n$5\n$150",
    "title": "1955 Wheat Penny Coin Value (Errors List, \"D\", \"S\" & No Mint Mark ...",
    "link": "https://www.coinvaluechecker.com/how-much-is-a-1955-wheat-penny-worth/"
  },
  "organic": [
    {
      "title": "1955 D Lincoln Wheat Penny Coin Value Prices, Photos & Info",
      "link": "https://www.usacoinbook.com/coins/481/small-cents/lincoln-wheat-cent/1955-D/",
      "snippet": "USA Coin Book Estimated Value of 1955-D Lincoln Wheat Penny is Worth $0.06 in Average Condition and can be Worth $0.42 to $1.22 or more in Uncirculated ...",
      "position": 1
    },
    {
      "title": "1955-D 1C, RD (Regular Strike) Lincoln Cent (Wheat Reverse)",
      "link": "https://www.pcgs.com/coinfacts/coin/1955-d-1c-rd/2830",
      "snippet": "The designer was Victor David Brenner for PCGS #2830. Visit to see edge, weight, diameter, auction records, price guide values and more for this coin.",
      "position": 2
    },
    {
      "title": "These Rare 1955 Wheat Pennies In Your Coin Collection ... - WMMR",
      "link": "https://wmmr.com/2023/04/21/these-rare-1955-wheat-pennies-in-your-coin-collection-could-be-worth-20000-or-more/",
      "snippet": "If your 1955 Wheat Pennies are beat up, it should still be worth at least a couple thousand. Perfect condition can be valued up to $288,000.",
      "date": "Apr 21, 2023",
      "position": 3
    },
    {
      "title": "Lincoln Wheat Penny Denver 1955 US Coin Errors for sale - eBay",
      "link": "https://www.ebay.com/b/Lincoln-Wheat-Penny-Denver-1955-US-Coin-Errors/524/bn_112545477",
      "snippet": "1955 D Lincoln Penny ~ Multi Error DDO/DDR Rare Error Coin. $30.00. or Best Offer. $4.33 shipping. 0 bids.",
      "position": 4
    },
    {
      "title": "1955 D Penny . What to look for : r/coins - Reddit",
      "link": "https://www.reddit.com/r/coins/comments/1ezuas5/1955_d_penny_what_to_look_for/",
      "snippet": "That penny is worth about 3 cents because that's what it's worth in copper weight. There were over 500 million of them minted so they aren't particularly ...",
      "date": "Aug 24, 2024",
      "sitelinks": [
        {
          "title": "I found a 1955 penny with a “D” on it is it worth anything?",
          "link": "https://www.reddit.com/r/CURRENCY/comments/1b4b6ew/i_found_a_1955_penny_with_a_d_on_it_is_it_worth/"
        },
        {
          "title": "How much is this (1955 D wheat penny) worth? : r/coins",
          "link": "https://www.reddit.com/r/coins/comments/ccc2lu/how_much_is_this_1955_d_wheat_penny_worth/"
        }
      ],
      "position": 5
    },
    {
      "title": "1955 D Wheat Penny Value - Bullion Shark",
      "link": "https://bullionsharks.com/1955-d-wheat-penny/?srsltid=AfmBOookkV2y34tI1Lc1EIO53PeOWp2SdPH4eoafH6mrOizFc2L7HCuU",
      "snippet": "As of 2024, the value of a 1955-D Wheat Penny typically ranges from $0.10 to $2 in circulated condition. Uncirculated examples can be worth between $2 and $10 ...",
      "position": 6
    },
    {
      "title": "1955 D Lincoln Wheat Penny Cent NGC Grade MS 66 RD Red Old ...",
      "link": "https://www.pcgs.com/auctionprices/item/1955-d-1c-rd/37924/-7365689524039320948",
      "snippet": "1955 D Lincoln Wheat Penny Cent NGC Grade MS 66 RD Red Old Label Uncirculated 1c. Lot # 283012806865. Grade MS66RD. Sale Price $14.99.",
      "position": 7
    },
    {
      "title": "Check the Value of your 1955 D Lincoln Wheat Penny in 2025 (Up ...",
      "link": "https://www.coleccionistasdemonedas.com/en/check-the-value-of-your-1955-d-lincoln-wheat-penny/",
      "snippet": "Well, this year, 2023, a 1955-D/D RPM Lincoln Cent graded by PCGS as MS66 RD sold for $1,900 on the eBay website. This price is in line with ...",
      "date": "Dec 29, 2024",
      "sitelinks": [
        {
          "title": "How much is a 1955-d lincoln...",
          "link": "https://www.coleccionistasdemonedas.com/en/check-the-value-of-your-1955-d-lincoln-wheat-penny/#How_much_is_a_1955-d_lincoln_wheat_penny_worth"
        },
        {
          "title": "What should you value if you...",
          "link": "https://www.coleccionistasdemonedas.com/en/check-the-value-of-your-1955-d-lincoln-wheat-penny/#What_should_you_value_if_you_want_to_invest_in_the_1955_lincoln_wheat_penny"
        }
      ],
      "position": 8
    },
    {
      "title": "1955-D 1c MS RD - Greysheet",
      "link": "https://www.greysheet.com/prices/item/1955-d-1c-lincoln-cent-with-red-surfaces/gsid/2168",
      "snippet": "Silver: $32.45 ; Platinum: $953.00 ; Denomination: 1c / Cent ; Mint Mark: D ; Mint Location: Denver.",
      "position": 9
    }
  ],
  "peopleAlsoAsk": [
    {
      "question": "What is the error on a 1955 D penny?",
      "snippet": "In 1955, one of the working obverse dies at the Philadelphia Mint was misaligned on the second blow from the working hub, thus resulting in a doubled image.",
      "title": "1955 doubled die cent - Wikipedia",
      "link": "https://en.wikipedia.org/wiki/1955_doubled_die_cent"
    },
    {
      "question": "How much is a 1955 D penny worth today?",
      "snippet": "What is the value of a 1955-D Wheat Penny? As of 2024, the value of a 1955-D Wheat Penny typically ranges from $0.10 to $2 in circulated condition. Uncirculated examples can be worth between $2 and $10 or more, depending on their quality.",
      "title": "1955 D Wheat Penny Value - Bullion Shark",
      "link": "https://bullionsharks.com/1955-d-wheat-penny/"
    },
    {
      "question": "How do I know if my 1955 penny is valuable?",
      "snippet": "A common misconception about the 1955 Wheat Penny value is that all 1955 pennies are worth a lot of money. In reality, it's the specific Double Die obverse error coin that holds significant value, while regular 1955 Wheat Pennies in circulated condition are relatively common and not as valuable.",
      "title": "1955 Wheat Penny Value | Bullion Shark",
      "link": "https://bullionsharks.com/1955-wheat-penny/"
    },
    {
      "question": "What year is penny worth $50,000?",
      "snippet": "The 1959-D wheat penny is one of the most controversial mule coins ever. It's worth $50,000! Here's everything you could possibly want to know about the 1959-D penny error!",
      "title": "This 1959-D Wheat Penny Is A Mule Coin Worth $50,000 ... - Pinterest",
      "link": "https://www.pinterest.com/pin/838091811889094578/"
    }
  ],
  "relatedSearches": [
    {
      "query": "How much is a 1955 d penny worth today"
    },
    {
      "query": "How much is a 1955 d penny worth with no mint"
    },
    {
      "query": "1955 D penny error"
    },
    {
      "query": "How much is a 1955 d penny worth e pluribus"
    },
    {
      "query": "Extremely rare 1955 D Lincoln Wheat penny with missing letter"
    },
    {
      "query": "1955 penny D"
    },
    {
      "query": "How much is a 1955 Wheat Penny worth"
    },
    {
      "query": "1955-D Wheat penny error varieties"
    }
  ],
  "credits": 1
}